pycissa/__init__.py
pycissa/postprocessing/__init__.py
pycissa/postprocessing/frequency_time/__init__.py
pycissa/postprocessing/frequency_time/frequency_time.py
pycissa/postprocessing/grouping/__init__.py
pycissa/postprocessing/grouping/grouping_functions.py
pycissa/postprocessing/monte_carlo/__init__.py
pycissa/postprocessing/monte_carlo/fractal_surrogates.py
pycissa/postprocessing/monte_carlo/montecarlo.py
pycissa/postprocessing/monte_carlo/surrogates.py
pycissa/postprocessing/periodogram/periodogram.py
pycissa/postprocessing/periodogram/travel_time_distributions.py
pycissa/postprocessing/predict/predict.py
pycissa/postprocessing/statistics/__init__.py
pycissa/postprocessing/statistics/autocorrelation_function.py
pycissa/postprocessing/statistics/average_mutual_information.py
pycissa/postprocessing/statistics/ljung_box.py
pycissa/postprocessing/statistics/normality_tests.py
pycissa/postprocessing/statistics/von_neumann.py
pycissa/postprocessing/trend/__init__.py
pycissa/postprocessing/trend/trend_functions.py
pycissa/preprocessing/__init__.py
pycissa/preprocessing/data_cleaning/__init__.py
pycissa/preprocessing/data_cleaning/data_cleaning.py
pycissa/preprocessing/gap_fill/__init__.py
pycissa/preprocessing/gap_fill/gap_filling.py
pycissa/processing/__init__.py
pycissa/processing/cissa/__init__.py
pycissa/processing/cissa/cissa.py
pycissa/processing/cissa_overlap/__init__.py
pycissa/processing/matrix_operations/__init__.py
pycissa/processing/matrix_operations/matrix_operations.py
pycissa/processing/mcissa/__init__.py
pycissa/utilities/__init__.py
pycissa/utilities/autoregression_functions.py
pycissa/utilities/date_time_utilities.py
pycissa/utilities/extendseries.py
pycissa/utilities/generate_cissa_result_dictionary.py
pycissa/utilities/helper_functions.py
pycissa/utilities/plotting.py
pycissa-0.1.1.dist-info/METADATA
pycissa-0.1.1.dist-info/WHEEL
pycissa-0.1.1.dist-info/RECORD
