Metadata-Version: 2.1
Name: pycissa
Version: 0.1.1
Summary: A Python implementation of the Circulant singular spectrum analysis (CiSSA) algorithm (https://github.com/jbogalo/CiSSA)
Home-page: https://github.com/LukeAFullard/pyCiSSA
License: CC0-1.0
Keywords: CiSSA,SSA,time-series,signal-processing,denoising,detrending
Author: Luke Fullard
Author-email: lukeafullard@gmail.com
Requires-Python: >=3.10,<4.0
Classifier: License :: CC0 1.0 Universal (CC0 1.0) Public Domain Dedication
Classifier: License :: Public Domain
Classifier: Operating System :: OS Independent
Classifier: Programming Language :: Python :: 3
Classifier: Programming Language :: Python :: 3.10
Classifier: Programming Language :: Python :: 3.11
Classifier: Programming Language :: Python :: 3.12
Requires-Dist: astropy (>6.1.3)
Requires-Dist: matplotlib (>=3.8.2,<4.0.0)
Requires-Dist: nolds (>=0.6.0,<0.7.0)
Requires-Dist: numpy (>1.26.2)
Requires-Dist: piecewise-regression (>=1.5.0,<2.0.0)
Requires-Dist: python-dateutil (>=2.8.2,<3.0.0)
Requires-Dist: requests (>=2.31.0,<3.0.0)
Requires-Dist: scikit-learn (>=1.5.1,<2.0.0)
Requires-Dist: scipy (>=1.11.4,<2.0.0)
Requires-Dist: statsmodels (>=0.14.1,<0.15.0)
Project-URL: Repository, https://github.com/LukeAFullard/pyCiSSA
